Metadata-Version: 2.1
Name: omnivista_py
Version: 0.3.8
Summary: A Python library that simplifies interaction with the OmniVista API, enabling easy authentication, device management, and performance data querying.
Home-page: https://github.com/phillipyosief/omnivista_py
Author: Phillip Jerome Yosief
Author-email: Phillip Jerome Yosief <phillip.yosief@outlook.com>
Project-URL: Homepage, https://github.com/phillipyosief/omnivista_py
Project-URL: Issues, https://github.com/phillipyosief/omnivista_py/issues
Keywords: OmniVista 2500,Alcatel API,Alcatel Python,Alcatel Lucent,Alcatel,OmniVista,API,network management,device management,performance data,automation,network monitoring,Python
Classifier: Programming Language :: Python :: 3
Classifier: License :: OSI Approved :: MIT License
Classifier: Operating System :: OS Independent
Requires-Python: >=3.9
License-File: LICENSE
